hyperyaml/__init__.py
hyperyaml/hyperyaml.py
hyperyaml/reader.py
hyperyaml/runner.py
hyperyaml/types.py
hyperyaml-0.1.dist-info/METADATA
hyperyaml-0.1.dist-info/WHEEL
hyperyaml-0.1.dist-info/top_level.txt
hyperyaml-0.1.dist-info/RECORD
